{"fonts/AcuminVariableConcept.otf":["fonts/AcuminVariableConcept.otf"],"images/aulastudio.png":["images/aulastudio.png"],"images/avatar.png":["images/avatar.png"],"images/bar.png":["images/bar.png"],"images/fede.png":["images/fede.png"],"images/giova.png":["images/giova.png"],"images/impl.png":["images/impl.png"],"images/palestra.png":["images/palestra.png"],"images/vitto.png":["images/vitto.png"],"packages/cupertino_icons/assets/CupertinoIcons.ttf":["packages/cupertino_icons/assets/CupertinoIcons.ttf"]}